read_pdz/__init__.py
read_pdz/_modidx.py
read_pdz/jpg_extractor.py
read_pdz/legacy.py
read_pdz/reader.py
read_pdz-0.0.5.dist-info/LICENSE
read_pdz-0.0.5.dist-info/METADATA
read_pdz-0.0.5.dist-info/WHEEL
read_pdz-0.0.5.dist-info/entry_points.txt
read_pdz-0.0.5.dist-info/top_level.txt
read_pdz-0.0.5.dist-info/RECORD
