Metadata-Version: 2.1
Name: read-pdz
Version: 0.0.5
Summary: Convert  Bruker XRF spectral data .pdz files into an open file format
Home-page: https://github.com/fligt/read_pdz
Author: Frank Ligterink
Author-email: frank.ligterink@gmail.com
License: MIT License
Keywords: nbdev jupyter notebook python XRF pdz-files
Classifier: Development Status :: 4 - Beta
Classifier: Intended Audience :: Developers
Classifier: Natural Language :: English
Classifier: Programming Language :: Python :: 3.7
Classifier: Programming Language :: Python :: 3.8
Classifier: Programming Language :: Python :: 3.9
Classifier: Programming Language :: Python :: 3.10
Classifier: License :: OSI Approved :: MIT License
Requires-Python: >=3.7
License-File: LICENSE
Requires-Dist: numpy
Requires-Dist: matplotlib
Requires-Dist: pandas
Requires-Dist: pillow
Requires-Dist: IPython
Provides-Extra: dev
